distant_frames/__init__.py
distant_frames/cli.py
distant_frames/core.py
distant_frames-0.2.2.dist-info/METADATA
distant_frames-0.2.2.dist-info/WHEEL
distant_frames-0.2.2.dist-info/entry_points.txt
distant_frames-0.2.2.dist-info/licenses/LICENSE
distant_frames-0.2.2.dist-info/RECORD
