Metadata-Version: 2.4
Name: distant-frames
Version: 0.2.2
Summary: Smart video frame extraction tool
Project-URL: Homepage, https://github.com/yubraaj11/distant-frames
Project-URL: Repository, https://github.com/yubraaj11/distant-frames
Project-URL: Issues, https://github.com/yubraaj11/distant-frames/issues
Project-URL: ReleaseNotes, https://github.com/yubraaj11/distant-frames/blob/main/RELEASE_NOTES.md
Author-email: Yubraj Sigdel <yubrajsigdel1@gmail.com>
License: GPL-3.0-or-later
License-File: LICENSE
Keywords: deduplication,frame-extraction,opencv,video,video-processing
Classifier: Development Status :: 3 - Alpha
Classifier: Intended Audience :: Developers
Classifier: License :: OSI Approved :: GNU General Public License v3 or later (GPLv3+)
Classifier: Programming Language :: Python :: 3
Classifier: Programming Language :: Python :: 3.12
Classifier: Topic :: Multimedia :: Video
Classifier: Topic :: Software Development :: Libraries :: Python Modules
Requires-Python: >=3.12
Requires-Dist: opencv-python>=4.10.0
Requires-Dist: typer>=0.9.0
